pykeyatome/__init__.py
pykeyatome/__main__.py
pykeyatome/client.py
pykeyatome-2.1.2.dist-info/LICENSE
pykeyatome-2.1.2.dist-info/METADATA
pykeyatome-2.1.2.dist-info/WHEEL
pykeyatome-2.1.2.dist-info/RECORD
