Metadata-Version: 2.1
Name: pykeyatome
Version: 2.1.2
Summary: A simple API for key atome electricity consumption
Home-page: https://github.com/jugla/pyKeyAtome
License: MIT
Author: jugla
Requires-Python: >=3.7.0,<3.20
Classifier: License :: OSI Approved :: MIT License
Classifier: Programming Language :: Python
Classifier: Programming Language :: Python :: 3
Classifier: Programming Language :: Python :: 3.7
Classifier: Programming Language :: Python :: 3.8
Classifier: Programming Language :: Python :: 3.9
Classifier: Programming Language :: Python :: 3.10
Classifier: Programming Language :: Python :: 3.11
Classifier: Programming Language :: Python :: 3
Classifier: Programming Language :: Python :: Implementation :: CPython
Classifier: Programming Language :: Python :: Implementation :: PyPy
Requires-Dist: fake-useragent (>=1.1.1,<2.0.0)
Requires-Dist: requests (>=2.22.0,<3.0.0)
Requires-Dist: simplejson (>=3.16.0,<4.0.0)
Project-URL: Repository, https://github.com/jugla/pyKeyAtome
